<?xml version="1.0" encoding="UTF-8"?><EXCEPTIONS DATETIME="28/03/16 21.43.42"><EXCEPTION ID = "0" IDREF="0" DESCRIPTION="" SOURCE="DATETIME="28/03/16 21.38.24"><DETAILS><FILE>E:\DOCUMENTI\TEMP\Programmazione\KR\V\Varie&#32;Banca&#32;e&#32;Carte.txt</FILE></DETAILS></EXCEPTION>
<EXCEPTION ID = "0" IDREF="20" DESCRIPTION="Resume&#32;senza&#32;Error" SOURCE="KrtDATETIME="28/03/16 21.38.24"><DETAILS><FILE>E:\DOCUMENTI\TEMP\Programmazione\KR\V\Varie&#32;Banca&#32;e&#32;Carte.txt</FILE></DETAILS></EXCEPTION>
</EXCEPTIONS>
